xaal/__init__.py
xaal/warp10/__init__.py
xaal/warp10/__main__.py
xaal/warp10/delete.py
xaal/warp10/dev.py
xaal_warp10-0.2.3.dist-info/METADATA
xaal_warp10-0.2.3.dist-info/WHEEL
xaal_warp10-0.2.3.dist-info/top_level.txt
xaal_warp10-0.2.3.dist-info/RECORD
